.bumpversion.cfg
.coveragerc
.pre-commit-config.yaml
.travis.yml
AUTHORS
ChangeLog
LICENSE
README.rst
requirements.txt
setup.cfg
setup.py
tox.ini
flymock/__init__.py
flymock.egg-info/PKG-INFO
flymock.egg-info/SOURCES.txt
flymock.egg-info/dependency_links.txt
flymock.egg-info/not-zip-safe
flymock.egg-info/pbr.json
flymock.egg-info/requires.txt
flymock.egg-info/top_level.txt
tests/__init__.py
tests/fly_mock_test.py
tests/integrate_test.py
tests/loader_test.py
tests/__mock__/demo.json
tests/__mock__/example.com.yaml
tests/__mock__/github.com.yaml